odoo/addons/stock_storage_type/README.rst
odoo/addons/stock_storage_type/__init__.py
odoo/addons/stock_storage_type/__manifest__.py
odoo/addons/stock_storage_type/demo/product_packaging.xml
odoo/addons/stock_storage_type/demo/stock_location.xml
odoo/addons/stock_storage_type/demo/stock_location_storage_type.xml
odoo/addons/stock_storage_type/demo/stock_package_storage_type.xml
odoo/addons/stock_storage_type/i18n/it.po
odoo/addons/stock_storage_type/i18n/stock_storage_type.pot
odoo/addons/stock_storage_type/models/__init__.py
odoo/addons/stock_storage_type/models/product_packaging.py
odoo/addons/stock_storage_type/models/stock_location.py
odoo/addons/stock_storage_type/models/stock_location_storage_type.py
odoo/addons/stock_storage_type/models/stock_package_storage_type.py
odoo/addons/stock_storage_type/readme/CONFIGURATION.rst
odoo/addons/stock_storage_type/readme/CONTRIBUTORS.rst
odoo/addons/stock_storage_type/readme/DESCRIPTION.rst
odoo/addons/stock_storage_type/readme/ROADMAP.rst
odoo/addons/stock_storage_type/security/ir.model.access.csv
odoo/addons/stock_storage_type/static/description/icon.png
odoo/addons/stock_storage_type/static/description/index.html
odoo/addons/stock_storage_type/views/product_packaging.xml
odoo/addons/stock_storage_type/views/stock_location.xml
odoo/addons/stock_storage_type/views/stock_location_storage_type.xml
odoo/addons/stock_storage_type/views/stock_package_storage_type.xml
odoo/addons/stock_storage_type/views/stock_picking.xml
odoo/addons/stock_storage_type/views/storage_type_menus.xml
odoo12_addon_stock_storage_type-12.0.1.0.0.99.dev10.dist-info/METADATA
odoo12_addon_stock_storage_type-12.0.1.0.0.99.dev10.dist-info/WHEEL
odoo12_addon_stock_storage_type-12.0.1.0.0.99.dev10.dist-info/top_level.txt
odoo12_addon_stock_storage_type-12.0.1.0.0.99.dev10.dist-info/RECORD
